psycopol_synth/__init__.py
psycopol_synth/main.py
psycopol_synth/prompts.py
psycopol_synth-2025.12.22081424.dist-info/METADATA
psycopol_synth-2025.12.22081424.dist-info/WHEEL
psycopol_synth-2025.12.22081424.dist-info/top_level.txt
psycopol_synth-2025.12.22081424.dist-info/RECORD
