Metadata-Version: 2.4
Name: psycopol-synth
Version: 2025.12.22081424
Summary: psycopol-synth analyzes psychological-political theories, extracting concepts and relationships to provide clear structured summaries.
Author-email: psycopol-synth <hi@eugene.plus>
License: MIT
Project-URL: Homepage, https://github.com/chigwell/psycopol-synth
Requires-Python: >=3.9
Requires-Dist: langchain-llm7>=0.0.0
Requires-Dist: llmatch-messages>=0.0.0
Requires-Dist: langchain-core>=0.3.0
